dash_chat/ChatComponent.py
dash_chat/ChatMessageInput.py
dash_chat/DotsIndicator.py
dash_chat/SpinnerIndicator.py
dash_chat/__init__.py
dash_chat/_imports_.py
dash_chat/dash_chat.min.js
dash_chat/dash_chat.min.js.map
dash_chat/metadata.json
dash_chat/package-info.json
dash_chat-0.3.0.dist-info/licenses/LICENSE.txt
dash_chat-0.3.0.dist-info/METADATA
dash_chat-0.3.0.dist-info/WHEEL
dash_chat-0.3.0.dist-info/top_level.txt
dash_chat-0.3.0.dist-info/RECORD
