Metadata-Version: 2.4
Name: dash-chat
Version: 0.3.0
Summary: A chat component for Dash
Author: Gbolahan Okerayi <okerayigbolahan@gmail.com>
License: MIT
Project-URL: Source Code, https://github.com/gbolly/dash-chat
Classifier: Programming Language :: Python :: 3
Classifier: Programming Language :: Python :: 3 :: Only
Classifier: Programming Language :: Python :: 3.9
Classifier: Programming Language :: Python :: 3.10
Classifier: Programming Language :: Python :: 3.11
Classifier: Programming Language :: Python :: 3.12
Classifier: Programming Language :: Python :: 3.13
Classifier: Framework :: Dash
License-File: LICENSE.txt
Dynamic: author
Dynamic: classifier
Dynamic: description
Dynamic: description-content-type
Dynamic: license
Dynamic: license-file
Dynamic: project-url
Dynamic: summary
